chakraversiontracker/__init__.py
chakraversiontracker/__main__.py
chakraversiontracker/_version.py
chakraversiontracker/data.json
chakraversiontracker/templates/packages.cli
chakraversiontracker/templates/packages.txt
chakraversiontracker/templates/repositories.cli
chakraversiontracker/templates/repositories.txt
chakraversiontracker-1.2.1.20160917.dist-info/DESCRIPTION.rst
chakraversiontracker-1.2.1.20160917.dist-info/METADATA
chakraversiontracker-1.2.1.20160917.dist-info/RECORD
chakraversiontracker-1.2.1.20160917.dist-info/WHEEL
chakraversiontracker-1.2.1.20160917.dist-info/entry_points.txt
chakraversiontracker-1.2.1.20160917.dist-info/metadata.json
chakraversiontracker-1.2.1.20160917.dist-info/top_level.txt
