Metadata-Version: 2.0
Name: chakraversiontracker
Version: 1.2.1.20160917
Summary: Software to detect packages in rolling repositories of Chakra that are out of date.
Home-page: http://chakra-version-tracker.rtfd.io/
Author: Adrián Chaves (Gallaecio)
Author-email: adriyetichaves@gmail.com
License: AGPLv3+
Download-URL: https://gitlab.com/gallaecio/chakraversiontracker/repository/archive.tar.gz?ref=v1.2.1.20160917
Platform: UNKNOWN
Classifier: Development Status :: 5 - Production/Stable
Classifier: Environment :: Console
Classifier: Intended Audience :: Developers
Classifier: License :: OSI Approved :: GNU Affero General Public License v3 or later (AGPLv3+)
Classifier: Operating System :: OS Independent
Classifier: Programming Language :: Python
Classifier: Programming Language :: Python :: 3
Classifier: Topic :: System :: Archiving :: Packaging
Requires-Dist: beautifulsoup4
Requires-Dist: jinja2
Requires-Dist: lxml
Requires-Dist: sphinx-argparse
Requires-Dist: termcolor
Requires-Dist: versiontracker
